setup.cfg
setup.py
ebs_deploy/__init__.py
ebs_deploy.egg-info/PKG-INFO
ebs_deploy.egg-info/SOURCES.txt
ebs_deploy.egg-info/dependency_links.txt
ebs_deploy.egg-info/requires.txt
ebs_deploy.egg-info/top_level.txt
ebs_deploy/commands/__init__.py
ebs_deploy/commands/delete_application_command.py
ebs_deploy/commands/delete_environment_command.py
ebs_deploy/commands/deploy_command.py
ebs_deploy/commands/describe_events_command.py
ebs_deploy/commands/dump_command.py
ebs_deploy/commands/help_command.py
ebs_deploy/commands/init_command.py
ebs_deploy/commands/list_environments_command.py
ebs_deploy/commands/list_solution_stacks_command.py
ebs_deploy/commands/list_versions_command.py
ebs_deploy/commands/rebuild_command.py
ebs_deploy/commands/swap_urls_command.py
ebs_deploy/commands/update_command.py
ebs_deploy/commands/update_environments_command.py
ebs_deploy/commands/wait_for_environment_command.py
ebs_deploy/commands/zdt_deploy_command.py
scripts/ebs-deploy