Metadata-Version: 1.1
Name: ebs-deploy
Version: 2.0.1
Summary: Python based command line tools for managing Amazon Elastic Beanstalk applications.
Home-page: https://github.com/briandilley/ebs-deploy
Author: Brian C. Dilley
Author-email: brian.dilley@gmail.com
License: UNKNOWN
Download-URL: https://github.com/briandilley/ebs-deploy
Platform: any
Classifier: Intended Audience :: Developers
